{"records": [{"id": 1748, "geometry": {"type": "Point", "coordinates": [11.137078, 46.154645]}, "name": "Mosana", "geo": "Mosana Giovo"}, {"id": 1749, "geometry": {"type": "Point", "coordinates": [11.1425, 46.159444]}, "name": "Pal\u00f9", "geo": "Pal&ugrave; di Giovo"}, {"id": 1750, "geometry": {"type": "Point", "coordinates": [11.160123, 46.160235]}, "name": "Valternigo", "geo": "Valternigo"}, {"id": 1751, "geometry": {"type": "Point", "coordinates": [11.154259, 46.158093]}, "name": "Verla", "geo": "Verla di Giovo"}, {"id": 1752, "geometry": {"type": "Point", "coordinates": [11.157935, 46.167404]}, "name": "Ville", "geo": "Ville di Giovo"}, {"id": 1753, "geometry": {"type": "Point", "coordinates": [11.152455, 46.155879]}, "name": "Lac de Montesel", "geo": "Giovo"}, {"id": 1754, "geometry": {"type": "Point", "coordinates": [11.152455, 46.155879]}, "name": "Monte Mancabrot", "geo": "Giovo"}, {"id": 1757, "geometry": {"type": "Point", "coordinates": [11.152455, 46.155879]}, "name": "Monte Corona", "geo": "Giovo"}, {"id": 1758, "geometry": {"type": "Point", "coordinates": [11.152455, 46.155879]}, "name": "Servizio Igiene Pubblica", "geo": "Giovo"}, {"id": 1760, "geometry": {"type": "Point", "coordinates": [11.152455, 46.155879]}, "name": "Ambulatorio infermieristico", "geo": "Giovo"}, {"id": 1761, "geometry": {"type": "Point", "coordinates": [11.22245, 46.175284]}, "name": "Distretto sanitario", "geo": "Cembra"}, {"id": 1762, "geometry": {"type": "Point", "coordinates": [11.154259, 46.158093]}, "name": "Farmacia", "geo": "Via Ai Molini 1 - 38030 Verla (TN)"}, {"id": 1764, "geometry": {"type": "Point", "coordinates": [11.220568, 46.175252]}, "name": "Guardia medica", "geo": "Piazza Marconi, 7 Cembra"}, {"id": 1765, "geometry": {"type": "Point", "coordinates": [11.152455, 46.155879]}, "name": "Pediatra", "geo": "Giovo"}, {"id": 1767, "geometry": {"type": "Point", "coordinates": [11.22245, 46.175284]}, "name": "Veterinario", "geo": "Cembra"}, {"id": 1768, "geometry": {"type": "Point", "coordinates": [11.104192, 46.151925]}, "name": "Scuola primaria di Giovo", "geo": "Via Oratorio, 15 Giovo"}, {"id": 1769, "geometry": {"type": "Point", "coordinates": [11.152455, 46.155879]}, "name": "Scuola secondaria di primo grado di Giovo ", "geo": "Giovo"}, {"id": 1770, "geometry": {"type": "Point", "coordinates": [11.172419, 46.160217]}, "name": "Asilo nido di Giovo \"Sandra Gottardi\"", "geo": "Via Devigili, 4 Ceola di Giovo"}, {"id": 1774, "geometry": {"type": "Point", "coordinates": [11.09315, 46.21776]}, "name": "Corpo di Polizia Locale \"Rotaliana Koenigsberg\"", "geo": "Mezzolombardo, Via Perlasca, 13"}, {"id": 1775, "geometry": {"type": "Point", "coordinates": [11.16748, 46.17886]}, "name": "Campo sportivo di Masen", "geo": "Masen Giovo"}, {"id": 1776, "geometry": {"type": "Point", "coordinates": [11.171944, 46.160278]}, "name": "Campo di calcetto di Ceola", "geo": "Ceola"}, {"id": 1777, "geometry": {"type": "Point", "coordinates": [11.1425, 46.159444]}, "name": "Palazzetto dello sport di Pal\u00f9", "geo": " Pal&ugrave; di Giovo"}, {"id": 1778, "geometry": {"type": "Point", "coordinates": [11.137078, 46.154645]}, "name": "Campo da tennis/calcetto e bocciofila a Mosana", "geo": "Mosana di Giovo"}, {"id": 1779, "geometry": {"type": "Point", "coordinates": [11.157935, 46.167404]}, "name": "Campo di calcetto di Ville", "geo": "Ville di Giovo"}, {"id": 1780, "geometry": {"type": "Point", "coordinates": [11.160123, 46.160235]}, "name": "Campo da bocce di Valternigo loc S.Floriano", "geo": "Valternigo "}, {"id": 1782, "geometry": {"type": "Point", "coordinates": [11.152455, 46.155879]}, "name": "Azienda Agricola Devigili Elio", "geo": "Giovo 38030 - Maso Belvedere"}, {"id": 1783, "geometry": {"type": "Point", "coordinates": [11.140595, 46.158293]}, "name": "Azienda Agricola Simoni", "geo": "Piazza degli Alpini, 14 - Pal&ugrave; di Giovo"}, {"id": 1784, "geometry": {"type": "Point", "coordinates": [11.154259, 46.158093]}, "name": "Azienda Vinicola \"Villa Corniole\"", "geo": "Verla di Giovo"}, {"id": 1785, "geometry": {"type": "Point", "coordinates": [11.123637, 46.174406]}, "name": "Azienda Vinicola biologica \"Molino dei Lessi\"", "geo": "Sorni di Lavis"}, {"id": 1786, "geometry": {"type": "Point", "coordinates": [11.154259, 46.158093]}, "name": "Opera Vitivinicola in Val di Cembra", "geo": "Verla di Giovo"}, {"id": 1739, "geometry": {"type": "Point", "coordinates": [11.22209, 46.17513]}, "name": "Apt Pin\u00e8 - Valle di Cembra", "geo": "Piazza Toniolli, 2 38034 Cembra"}, {"id": 1740, "geometry": {"type": "Point", "coordinates": [11.154259, 46.158093]}, "name": "Chiesa di Santa Maria Assunta", "geo": "Verla di Giovo"}, {"id": 1741, "geometry": {"type": "Point", "coordinates": [11.167909, 46.172602]}, "name": "Chiesa di S. Floriano", "geo": "san Floriano Giovo"}, {"id": 1742, "geometry": {"type": "Point", "coordinates": [11.154259, 46.158093]}, "name": "Chiesa di Sant'Antonio", "geo": "Verla di Giovo"}, {"id": 1743, "geometry": {"type": "Point", "coordinates": [11.157935, 46.167404]}, "name": "Castel Giovo", "geo": "Ville di Giovo"}, {"id": 1744, "geometry": {"type": "Point", "coordinates": [11.152455, 46.155879]}, "name": "Chiesa di San Giorgio", "geo": "Giovo"}, {"id": 1746, "geometry": {"type": "Point", "coordinates": [11.171944, 46.160278]}, "name": "Ceola", "geo": "Ceola (tn)"}, {"id": 1747, "geometry": {"type": "Point", "coordinates": [11.16748, 46.17886]}, "name": "Masen", "geo": "Masen Giovo"}, {"id": 2372, "geometry": {"type": "Point", "coordinates": [11.14342, 46.159716]}, "name": "Campo da tennis/pallavolo/calcetto e basket a Pal\u00f9", "geo": "Via delle Scuole, Pal&ugrave; di Giovo"}, {"id": 2423, "geometry": {"type": "Point", "coordinates": [11.154259, 46.158093]}, "name": "Festa dell'uva", "geo": "Verla di Giovo, Trentino, Italia"}, {"id": 2424, "geometry": {"type": "Point", "coordinates": [11.157935, 46.167404]}, "name": "Madonna addolorata a Ville di Giovo", "geo": "Ville di Giovo, Trentino, Italia"}, {"id": 2474, "geometry": {"type": "Point", "coordinates": [11.15314, 46.156628]}, "name": "Studio dentistico", "geo": "via Principe Umberto, 9 Verla di Giovo, Italia"}, {"id": 2268, "geometry": {"type": "Point", "coordinates": [11.154259, 46.158093]}, "name": "El Sagron", "geo": "Verla di Giovo, Trentino, Italia"}, {"id": 2269, "geometry": {"type": "Point", "coordinates": [11.143254, 46.159299]}, "name": "Quarta de lui"}, {"id": 2301, "geometry": {"type": "Point", "coordinates": [11.157935, 46.167404]}, "name": "Ville bassa", "geo": "Ville di Giovo"}, {"id": 2302, "geometry": {"type": "Point", "coordinates": [11.157935, 46.167404]}, "name": "Ville alta", "geo": "Ville di Giovo"}, {"id": 2303, "geometry": {"type": "Point", "coordinates": [11.16748, 46.17886]}, "name": "Masen", "geo": "Masen di Giovo"}, {"id": 2304, "geometry": {"type": "Point", "coordinates": [11.160123, 46.160235]}, "name": "Valternigo", "geo": "Valternigo di Giovo"}, {"id": 2305, "geometry": {"type": "Point", "coordinates": [11.170758, 46.159791]}, "name": "Ceola", "geo": "Ceola di Giovo"}, {"id": 2306, "geometry": {"type": "Point", "coordinates": [11.137078, 46.154645]}, "name": "Mosana", "geo": "Mosana di Giovo, Trento"}, {"id": 2307, "geometry": {"type": "Point", "coordinates": [11.156261, 46.155995]}, "name": "Verla", "geo": "via al doss Pules, Verla di Giovo"}, {"id": 2308, "geometry": {"type": "Point", "coordinates": [11.142706, 46.158365]}, "name": "Pal\u00f9", "geo": "via Carraia, Pal&ugrave; di Giovo"}, {"id": 2542, "geometry": {"type": "Point", "coordinates": [11.140308, 46.166992]}, "name": "Serci"}, {"id": 1759, "geometry": {"type": "Point", "coordinates": [11.152455, 46.155879]}, "name": "Medici di base", "geo": "Giovo"}]}